{
	"animations": [
		{
			"loop": false,
			"offsets": [
				25,
				19
			],
			"anim": "idle",
			"fps": 24,
			"name": "idle",
			"indices": []
		},
		{
			"loop": false,
			"offsets": [
				111,
				-2
			],
			"anim": "singLEFT",
			"fps": 24,
			"name": "left",
			"indices": []
		},
		{
			"loop": false,
			"offsets": [
				54,
				10
			],
			"anim": "singRIGHT",
			"fps": 24,
			"name": "right",
			"indices": []
		},
		{
			"loop": false,
			"offsets": [
				105,
				104
			],
			"anim": "singUP",
			"fps": 24,
			"name": "up",
			"indices": []
		},
		{
			"loop": false,
			"offsets": [
				73,
				-9
			],
			"anim": "singDOWN",
			"fps": 24,
			"name": "down",
			"indices": []
		}
	],
	"vocals_file": "",
	"no_antialiasing": false,
	"image": "characters/Morty1",
	"position": [
		150,
		380
	],
	"healthicon": "morty",
	"flip_x": false,
	"healthbar_colors": [
		252,
		252,
		105
	],
	"camera_position": [
		-40,
		-310
	],
	"sing_duration": 4,
	"scale": 2.25,
	"_editor_isPlayer": false
}